cosmofoptscope/__init__.py
cosmofoptscope/find_fopt.py
cosmofoptscope/potential.py
cosmofoptscope-0.3.2.dist-info/METADATA
cosmofoptscope-0.3.2.dist-info/WHEEL
cosmofoptscope-0.3.2.dist-info/licenses/LICENSE
cosmofoptscope-0.3.2.dist-info/RECORD
