Metadata-Version: 2.4
Name: cosmofoptscope
Version: 0.3.2
Summary: A tool for detecting and analyzing First Order Phase Transitions (FOPT) in cosmic evolution using the cosmoTransitions library.
Project-URL: Homepage, https://github.com/hiilynn/cosmoT-FOPTscope
Author-email: yeji PARK <yeji.park.yeji@gmail.com>
License-File: LICENSE
Classifier: License :: OSI Approved :: MIT License
Classifier: Operating System :: OS Independent
Classifier: Programming Language :: Python :: 3
Requires-Python: ==3.12.7
Requires-Dist: cosmotransitions>=2.0.7
Requires-Dist: numpy>=2.1.3
Requires-Dist: ray>=2.38.0
Requires-Dist: scipy>=1.14.1
